Metadata-Version: 2.4
Name: easy-start-sms
Version: 0.1.4
Summary: easy_start_sms 是一个用于短信集成的 Python 包，旨在简化常见的短信操作，如发送短信等。该包提供了直观的 API，支持 httpx 库。
Home-page: https://gitee.com/guolei19850528/easy_start_sms
Author: guolei
Author-email: 174000902@qq.com
Classifier: Programming Language :: Python :: 3
Classifier: License :: OSI Approved :: MIT License
Classifier: Operating System :: OS Independent
Requires-Python: >=3.6
License-File: LICENSE
Requires-Dist: httpx
Requires-Dist: jsonschema
Dynamic: author
Dynamic: author-email
Dynamic: classifier
Dynamic: description
Dynamic: description-content-type
Dynamic: home-page
Dynamic: license-file
Dynamic: requires-dist
Dynamic: requires-python
Dynamic: summary
